live_Indonesia_earthquake/__init__.py
lshakeidn-0.2.2.dist-info/LICENSE
lshakeidn-0.2.2.dist-info/METADATA
lshakeidn-0.2.2.dist-info/WHEEL
lshakeidn-0.2.2.dist-info/top_level.txt
lshakeidn-0.2.2.dist-info/RECORD
