Metadata-Version: 2.1
Name: lshakeidn
Version: 0.2.2
Summary: This package gets the latest earthquake in Indonesia from the official government agency
Home-page: https://github.com/giesoko/live_indonesia_earthquake
Author: NaranggiSoko
Author-email: ranggi_me@yahoo.com
License: UNKNOWN
Project-URL: Website, https://pramudyasoko.blogspot.com/
Platform: UNKNOWN
Classifier: Programming Language :: Python :: 3
Classifier: License :: OSI Approved :: GNU General Public License v3 (GPLv3)
Classifier: Operating System :: OS Independent
Classifier: Development Status :: 4 - Beta
Requires-Python: >=3.6
License-File: LICENSE
